Metadata-Version: 2.1
Name: mpmath-with-autoprec-correction-lirikoknessu-fork
Version: 1.4.0a0
Summary: Python library for arbitrary-precision floating-point arithmetic. This fork implements fixes in auto precision setting
Author-email: Kirill Ussenko <kirill.ussenko@gmail.com>
License: BSD
Project-URL: Homepage, https://mpmath.org/
Project-URL: Source Code, https://github.com/mpmath/mpmath
Project-URL: Bug Tracker, https://github.com/mpmath/mpmath/issues
Project-URL: Fork Code, https://github.com/LlirikOknessu/mpmath/
Project-URL: Documentation, http://mpmath.org/doc/current/
Classifier: License :: OSI Approved :: BSD License
Classifier: Topic :: Scientific/Engineering :: Mathematics
Classifier: Topic :: Software Development :: Libraries :: Python Modules
Classifier: Programming Language :: Python
Classifier: Programming Language :: Python :: 3
Classifier: Programming Language :: Python :: 3 :: Only
Classifier: Programming Language :: Python :: 3.8
Classifier: Programming Language :: Python :: 3.9
Classifier: Programming Language :: Python :: 3.10
Classifier: Programming Language :: Python :: 3.11
Classifier: Programming Language :: Python :: 3.12
Classifier: Programming Language :: Python :: Implementation :: CPython
Classifier: Programming Language :: Python :: Implementation :: PyPy
Requires-Python: >=3.8
License-File: LICENSE
Provides-Extra: ci
Requires-Dist: pytest-xdist ; extra == 'ci'
Provides-Extra: develop
Requires-Dist: mpmath[tests] ; extra == 'develop'
Requires-Dist: pytest-cov ; extra == 'develop'
Requires-Dist: wheel ; extra == 'develop'
Requires-Dist: build ; extra == 'develop'
Requires-Dist: flake518 >=1.5 ; (python_version >= "3.9") and extra == 'develop'
Provides-Extra: docs
Requires-Dist: sphinx ; extra == 'docs'
Provides-Extra: gmpy
Requires-Dist: gmpy2 >=2.1.0a4 ; (platform_python_implementation != "PyPy" and python_version < "3.12") and extra == 'gmpy'
Requires-Dist: gmpy2 >=2.2.0a1 ; (platform_python_implementation != "PyPy" and python_version >= "3.12") and extra == 'gmpy'
Provides-Extra: tests
Requires-Dist: pytest >=6 ; extra == 'tests'
Requires-Dist: numpy <=1.25.2 ; (python_version < "3.12") and extra == 'tests'
